{
    "/js/app.js": "/js/app.js",
    "/css/app.css": "/css/app.css",
    "/images/.DS_Store": "/images/.DS_Store",
    "/images/000304610027100x768-1581354443215.jpeg": "/images/000304610027100x768-1581354443215.jpeg",
    "/images/20210919_TT_HARVEST_156.jpeg": "/images/20210919_TT_HARVEST_156.jpeg",
    "/images/20210919_TT_HARVEST_207.jpeg": "/images/20210919_TT_HARVEST_207.jpeg",
    "/images/3042B731-4B9D-4BC0-B61F-6566702A1C69_1_105_c.jpeg": "/images/3042B731-4B9D-4BC0-B61F-6566702A1C69_1_105_c.jpeg",
    "/images/FONDUE_FINAL-110.jpeg": "/images/FONDUE_FINAL-110.jpeg",
    "/images/SP_AlexisPhoto_2.jpg": "/images/SP_AlexisPhoto_2.jpg",
    "/images/THIRSTY-11-spritz_cards.jpeg": "/images/THIRSTY-11-spritz_cards.jpeg",
    "/images/THIRSTY_FINAL-12.jpeg": "/images/THIRSTY_FINAL-12.jpeg",
    "/images/THIRSTY_FLOWER_SHOP-115.jpeg": "/images/THIRSTY_FLOWER_SHOP-115.jpeg",
    "/images/ThirstyThirsty_Logo_Circle-C.png": "/images/ThirstyThirsty_Logo_Circle-C.png",
    "/images/ThirstyThirsty_Logo_Stack.png": "/images/ThirstyThirsty_Logo_Stack.png",
    "/images/kim.jpg": "/images/kim.jpg",
    "/images/trian.jpg": "/images/trian.jpg"
}
